seven_jd/__init__.py
seven_jd/jd/__init__.py
seven_jd/jd/api/__init__.py
seven_jd/jd/api/base.py
seven_jd/jd/api/rest/ActyEnqueryRegistrationDataCountRequest.py
seven_jd/jd/api/rest/AfsserviceRefundinfoGetRequest.py
seven_jd/jd/api/rest/ApiSmsModelConfigReadServiceCountSmsModelConfigByParamsRequest.py
seven_jd/jd/api/rest/ApiSmsModelConfigReadServiceGetSmsModelConfigByParamsRequest.py
seven_jd/jd/api/rest/ApiSmsModelConfigWriteServiceSendSceneSmsRequest.py
seven_jd/jd/api/rest/ApiSmsModelConfigWriteServiceSendSmsRequest.py
seven_jd/jd/api/rest/ApplyAddMerchantsAddRequest.py
seven_jd/jd/api/rest/ApplyRepealSaveRequest.py
seven_jd/jd/api/rest/AreaCityGetRequest.py
seven_jd/jd/api/rest/AreaCountyGetRequest.py
seven_jd/jd/api/rest/AreaProvinceGetRequest.py
seven_jd/jd/api/rest/AreaTownGetRequest.py
seven_jd/jd/api/rest/ArealimitReadFindAreaLimitsByWareIdRequest.py
seven_jd/jd/api/rest/ArealimitWriteUpdateWareAreaLimitsRequest.py
seven_jd/jd/api/rest/AreasCityGetRequest.py
seven_jd/jd/api/rest/AreasCountyGetRequest.py
seven_jd/jd/api/rest/AreasOverseasCityGetRequest.py
seven_jd/jd/api/rest/AreasOverseasProvinceGetRequest.py
seven_jd/jd/api/rest/AreasProvinceGetRequest.py
seven_jd/jd/api/rest/AreasTownGetRequest.py
seven_jd/jd/api/rest/AscQueryListRequest.py
seven_jd/jd/api/rest/AscQueryViewRequest.py
seven_jd/jd/api/rest/AssetAccountBalanceQueryRequest.py
seven_jd/jd/api/rest/AssetActivityCancelRequest.py
seven_jd/jd/api/rest/AssetActivityCreateRequest.py
seven_jd/jd/api/rest/AssetActivityQueryRequest.py
seven_jd/jd/api/rest/AssetActivityUpdateRequest.py
seven_jd/jd/api/rest/AssetBenefitOrderQueryRequest.py
seven_jd/jd/api/rest/AssetBenefitQueryRequest.py
seven_jd/jd/api/rest/AssetBenefitSendRequest.py
seven_jd/jd/api/rest/AssetIsvAccountBalanceQueryRequest.py
seven_jd/jd/api/rest/AssetIsvActivityCreateRequest.py
seven_jd/jd/api/rest/AssetIsvActivityQueryRequest.py
seven_jd/jd/api/rest/AssetRiskVerifyRequest.py
seven_jd/jd/api/rest/AssetTypeQueryRequest.py
seven_jd-1.0.17.dist-info/LICENSE
seven_jd-1.0.17.dist-info/METADATA
seven_jd-1.0.17.dist-info/WHEEL
seven_jd-1.0.17.dist-info/top_level.txt
seven_jd-1.0.17.dist-info/RECORD
